[
  {
    "name": "PHYSICSENGINE",
    "description": "Simple physics engine in C++",
    "language": "C++",
    "lastUpdated": "Jan 7, 2026",
    "html_url": "https://github.com/jgkiran2003/PhysicsEngine"
  },
  {
    "name": "FINNEWS",
    "description": null,
    "language": "Python",
    "lastUpdated": "Dec 30, 2025",
    "html_url": "https://github.com/jgkiran2003/FinNews"
  },
  {
    "name": "DIGITAL-PA-SYSTEM",
    "description": null,
    "language": "JavaScript Other",
    "lastUpdated": "Feb 2, 2025",
    "html_url": "https://github.com/jgkiran2003/digital-pa-system"
  },
  {
    "name": "FINANCE",
    "description": null,
    "language": "HTML",
    "lastUpdated": "Jan 31, 2025",
    "html_url": "https://github.com/jgkiran2003/finance"
  }
]